opentapioca/__init__.py
opentapioca/classifier.py
opentapioca/cli.py
opentapioca/indexingprofile.py
opentapioca/languagemodel.py
opentapioca/mention.py
opentapioca/similarities.py
opentapioca/sparqlwikidata.py
opentapioca/tag.py
opentapioca/tagger.py
opentapioca/taggerfactory.py
opentapioca/typematcher.py
opentapioca/utils.py
opentapioca/wditem.py
opentapioca/wikidatagraph.py
opentapioca/readers/__init__.py
opentapioca/readers/apireaderbase.py
opentapioca/readers/dumpreader.py
opentapioca/readers/sparqlreader.py
opentapioca/readers/streamreader.py
opentapioca/tests/__init__.py
opentapioca/tests/test_classifier.py
opentapioca/tests/test_dumpreader.py
opentapioca/tests/test_fixtures.py
opentapioca/tests/test_indexingprofile.py
opentapioca/tests/test_languagemodel.py
opentapioca/tests/test_sparqlreader.py
opentapioca/tests/test_streamreader.py
opentapioca/tests/test_tagger.py
opentapioca/tests/test_taggerfactory.py
opentapioca/tests/test_typematcher.py
opentapioca/tests/test_wditem.py
opentapioca/tests/test_wikidatagraph.py
opentapioca-0.1.2.dist-info/LICENSE
opentapioca-0.1.2.dist-info/METADATA
opentapioca-0.1.2.dist-info/WHEEL
opentapioca-0.1.2.dist-info/entry_points.txt
opentapioca-0.1.2.dist-info/top_level.txt
opentapioca-0.1.2.dist-info/RECORD
