Metadata-Version: 2.1
Name: opentapioca
Version: 0.1.2
Summary: Simple entity linking service for Wikidata
Home-page: https://github.com/wetneb/opentapioca
Author: Antonin Delpeuch
Author-email: antonin@delpeuch.eu
License: MIT
Keywords: NIF NLP Wikidata NERD
Classifier: Development Status :: 3 - Alpha
Classifier: Intended Audience :: Developers
Classifier: Topic :: Scientific/Engineering :: Information Analysis
Classifier: License :: OSI Approved :: MIT License
Classifier: Programming Language :: Python :: 2
Classifier: Programming Language :: Python :: 2.7
Classifier: Programming Language :: Python :: 3
Classifier: Programming Language :: Python :: 3.3
Classifier: Programming Language :: Python :: 3.4
Classifier: Programming Language :: Python :: 3.5
Classifier: Programming Language :: Python :: 3.6
Classifier: Programming Language :: Python :: 3.7
License-File: LICENSE
Requires-Dist: numpy
Requires-Dist: scipy
Requires-Dist: scikit-learn
Requires-Dist: bottle
Requires-Dist: requests-cache
Requires-Dist: requests-mock
Requires-Dist: unidecode
Requires-Dist: pynif
Requires-Dist: requests
Requires-Dist: click
Requires-Dist: sseclient
Provides-Extra: dev
Requires-Dist: check-manifest ; extra == 'dev'
Provides-Extra: test
Requires-Dist: coverage ; extra == 'test'
Requires-Dist: pytest ; extra == 'test'
